CHANGES.txt
Kookbook.py
MANIFEST
MANIFEST.in
MIT-LICENSE
README.txt
ez_setup.py
setup.py
benchmark/Kookbook.py
benchmark/Makefile
benchmark/bench.py
benchmark/bench_context.py
benchmark/bench_context.yaml
benchmark/bench_pycode.py
benchmark/bench_pycode/pycode_01_append-line.py
benchmark/bench_pycode/pycode_02_append-multilines.py
benchmark/bench_pycode/pycode_03_extend-unbound.py
benchmark/bench_pycode/pycode_04_extend-bound.py
benchmark/bench_pycode/pycode_11_extend-str.py
benchmark/bench_pycode/pycode_12_extend-str-local.py
benchmark/bench_pycode/pycode_13_extend-format.py
benchmark/bench_pycode/pycode_14_append_format.py
benchmark/bench_pycode/pycode_15_extend-tostr.py
benchmark/bench_pycode/pycode_16_extend-tostr-local.py
benchmark/bench_pycode/pycode_21_escape-str.py
benchmark/bench_pycode/pycode_22_escape-tostr.py
benchmark/bench_pycode/pycode_23_webext-escape-tostr.py
benchmark/bench_pycode/pycode_24_webext-escape.py
benchmark/gae/Kookbook.py
benchmark/gae/app.yaml
benchmark/gae/bench_context.py
benchmark/gae/index.yaml
benchmark/gae/main.py
benchmark/gae/lib/tenjin.py
benchmark/gae/templates/bench_django.html
benchmark/gae/templates/bench_django12.html
benchmark/gae/templates/bench_jinja2.html
benchmark/gae/templates/bench_mako.html
benchmark/gae/templates/bench_safetenjin.pyhtml
benchmark/gae/templates/bench_tenjin.pyhtml
benchmark/gae/templates/escape_django.html
benchmark/gae/templates/escape_django12.html
benchmark/gae/templates/escape_jinja2.html
benchmark/gae/templates/escape_mako.html
benchmark/gae/templates/escape_safetenjin.pyhtml
benchmark/gae/templates/escape_tenjin.pyhtml
benchmark/gae/templates/stocks.pyhtml
benchmark/templates/_footer.html
benchmark/templates/_header.html
benchmark/templates/bench_cheetah.tmpl
benchmark/templates/bench_django.html
benchmark/templates/bench_genshi.html
benchmark/templates/bench_jinja2.html
benchmark/templates/bench_kid.kid
benchmark/templates/bench_mako.html
benchmark/templates/bench_myghty.myt
lib3/Tenjin.egg-info/PKG-INFO
lib3/Tenjin.egg-info/SOURCES.txt
lib3/Tenjin.egg-info/dependency_links.txt
lib3/Tenjin.egg-info/top_level.txt
